{
  "id": "uml-analysis/sequence-diagrams",
  "title": "Diagramme de séquence complémentaires",
  "description": "Les diagrammes de séquence présentés ici complètent ceux des use-cases en se concentrant sur les interactions cross-fonctionnelles, les patterns d'architecture système et les flux d'intégration complexes qui transcendent les fonctionnalités individuelles.",
  "source": "@site/docs/uml-analysis/sequence-diagrams.md",
  "sourceDirName": "uml-analysis",
  "slug": "/uml-analysis/sequence-diagrams",
  "permalink": "/RF_Go/uml-analysis/sequence-diagrams",
  "draft": false,
  "unlisted": false,
  "editUrl": "https://github.com/Beatwen/RF_Go/tree/main/docs/uml-analysis/sequence-diagrams.md",
  "tags": [],
  "version": "current",
  "frontMatter": {},
  "sidebar": "tutorialSidebar",
  "previous": {
    "title": "UC-010: Gestion des sessions RF",
    "permalink": "/RF_Go/uml-analysis/use-cases/uc-010"
  },
  "next": {
    "title": "Diagramme d'activité complémentaires",
    "permalink": "/RF_Go/uml-analysis/activity-diagrams"
  }
}